pdm_update_interactive.py
pdm_update_interactive-0.0.3.dist-info/LICENSE
pdm_update_interactive-0.0.3.dist-info/METADATA
pdm_update_interactive-0.0.3.dist-info/WHEEL
pdm_update_interactive-0.0.3.dist-info/entry_points.txt
pdm_update_interactive-0.0.3.dist-info/top_level.txt
pdm_update_interactive-0.0.3.dist-info/RECORD
