Metadata-Version: 2.1
Name: pdm-update-interactive
Version: 0.0.3
Home-page: https://github.com/q0w/pdm-update-interactive/
Author: q0w
License: MIT
Classifier: License :: OSI Approved :: MIT License
Classifier: Programming Language :: Python :: 3
Classifier: Programming Language :: Python :: 3 :: Only
Classifier: Topic :: Software Development :: Build Tools
Requires-Python: >=3.7
License-File: LICENSE
Requires-Dist: pdm (>=2)
Requires-Dist: questionary (>=1.10.0)
